labetl/__about__.py
labetl/__init__.py
labetl/bruker_ftir_parser.py
labetl/deatak_cone_parser.py
labetl/faa_mcc_parser.py
labetl/fox_hfm_parser.py
labetl/netzsch_sta_ngb_parser.py
labetl/netzsch_sta_parser.py
labetl/netzsch_sta_raw_parser_dev.py
labetl/util.py
labetl-0.0.3.dist-info/METADATA
labetl-0.0.3.dist-info/WHEEL
labetl-0.0.3.dist-info/licenses/LICENSE.txt
labetl-0.0.3.dist-info/RECORD
