Metadata-Version: 2.4
Name: labetl
Version: 0.0.3
Summary: ETL system for interpreting laboratory instrument data files and loading them into a standardized format while enforcing schema and retaining all metadata.
Project-URL: Documentation, https://github.com/ulfsri/lab-etl#readme
Project-URL: Issues, https://github.com/ulfsri/lab-etl/issues
Project-URL: Source, https://github.com/ulfsri/lab-etl
Author-email: GraysonBellamy <gbellamy@umd.edu>
License-File: LICENSE.txt
Classifier: Development Status :: 4 - Beta
Classifier: Programming Language :: Python
Classifier: Programming Language :: Python :: 3.10
Classifier: Programming Language :: Python :: 3.11
Classifier: Programming Language :: Python :: 3.12
Classifier: Programming Language :: Python :: Implementation :: CPython
Classifier: Programming Language :: Python :: Implementation :: PyPy
Requires-Python: >=3.10
Requires-Dist: brukeropus>=1.1.0
Requires-Dist: fastexcel>=0.12.1
Requires-Dist: numpy>=2.2.1
Requires-Dist: polars>=1.19.0
Requires-Dist: pyarrow>=18.1.0
Requires-Dist: python-dateutil>=2.9.0
Requires-Dist: python-magic>=0.4.27
Provides-Extra: docs
Requires-Dist: mkdocs-material>=9.5.49; extra == 'docs'
Requires-Dist: mkdocstrings[python]>=0.27.0; extra == 'docs'
